watchdog/__init__.py
watchdog/main.py
watchdog/tests/__init__.py
watchdog/tests/qdk_test.py
ar_watchdog-0.0.4.dist-info/LICENSE
ar_watchdog-0.0.4.dist-info/METADATA
ar_watchdog-0.0.4.dist-info/WHEEL
ar_watchdog-0.0.4.dist-info/top_level.txt
ar_watchdog-0.0.4.dist-info/RECORD
